APsystemsEZ1/__init__.py
apsystems_ez1-2.6.0.dist-info/LICENSE
apsystems_ez1-2.6.0.dist-info/METADATA
apsystems_ez1-2.6.0.dist-info/WHEEL
apsystems_ez1-2.6.0.dist-info/RECORD
