Metadata-Version: 2.3
Name: apsystems-ez1
Version: 2.6.0
Summary: The APsystems EZ1 Python library offers a streamlined interface for interacting with the local API of APsystems EZ1 Microinverters.
Author: Sonnenladen GmbH
Author-email: l.tiedt@sonnenladen.de
Requires-Python: >=3.11,<4.0
Classifier: License :: OSI Approved :: MIT License
Classifier: Programming Language :: Python :: 3
Classifier: Programming Language :: Python :: 3.11
Classifier: Programming Language :: Python :: 3.12
Classifier: Programming Language :: Python :: 3.13
Requires-Dist: aiohttp (>=3,<4)
